rumus/__init__.py
rumus/trapesium.py
gooddaycoklat-0.0.1.dist-info/LICENSE
gooddaycoklat-0.0.1.dist-info/METADATA
gooddaycoklat-0.0.1.dist-info/WHEEL
gooddaycoklat-0.0.1.dist-info/top_level.txt
gooddaycoklat-0.0.1.dist-info/RECORD
