Metadata-Version: 2.1
Name: gooddaycoklat
Version: 0.0.1
Summary: A simple library for calculating the area of ​​a trapezoid
Home-page: https://github.com/zaakyyz/gooddaycoklat/tree/main/Trap
Author: zaakyyz
Author-email: <muhammadzaky034@gmail.com>
License: MIT
Keywords: trap
Classifier: Development Status :: 1 - Planning
License-File: LICENSE
